{
    "client": {
        "view": "root",
        "views": {
            "root": {
                "branch": "bxbranch_",
                "user": "bxuser_",
                "cert": "bxcert_ZTRDYcNJFFkeGSmHae7o75i27",
                "key": "bxkey_jyxWVfBjx4vam8cU9t1oUpyVAx"
            }
        }
    },
    "server": {
        "sql": {
            "servers": [
                "localhost",
                "127.0.0.1"
            ],
            "username": "bxsql_user_",
            "password": "bxsql_pass_"
        }
    }
}